syntaxdb
