Metadata-Version: 1.1
Name: syntaxdb
Version: 0.1.1
Summary: A small Python library for accessing the SyntaxDB API
Home-page: https://github.com/lhat-messorem/syntax_db
Author: lhat-messorem
Author-email: lhat.messorem@gmail.com
License: MIT
Keywords: syntaxdb
Platform: UNKNOWN
Classifier: Intended Audience :: Developers
Classifier: Programming Language :: Python
Classifier: Topic :: Utilities
